nonebot_plugin_osuverify/__init__.py
nonebot_plugin_osuverify-0.1.3.dist-info/LICENSE
nonebot_plugin_osuverify-0.1.3.dist-info/METADATA
nonebot_plugin_osuverify-0.1.3.dist-info/WHEEL
nonebot_plugin_osuverify-0.1.3.dist-info/top_level.txt
nonebot_plugin_osuverify-0.1.3.dist-info/RECORD
