Metadata-Version: 2.1
Name: nonebot-plugin-osuverify
Version: 0.1.3
Summary: 通过osu!账号审核入群功能
Home-page: https://github.com/mas-alone/nonebot-plugin-sayoroll
Author: A M D
Author-email: mas_alone@qq.com
Classifier: Programming Language :: Python :: 3.8
Classifier: License :: OSI Approved :: GNU Affero General Public License v3
Classifier: Operating System :: OS Independent
License-File: LICENSE
Requires-Dist: httpx >=0.23.3
Requires-Dist: nonebot2 >=2.0.0rc3
Requires-Dist: nonebot-adapter-onebot >=2.0.0b1
